{"resourceType":"ValueSet","id":"pregnancies-summary-uv-ips","meta":{"profile":["http://hl7.org/fhir/StructureDefinition/shareablevalueset"]},"text":{"status":"generated","div":"<div xmlns=\"http://www.w3.org/1999/xhtml\"><ul><li>Include these codes as defined in <a href=\"http://loinc.org\"><code>http://loinc.org</code></a><table class=\"none\"><tr><td style=\"white-space:nowrap\"><b>Code</b></td><td><b>Display</b></td></tr><tr><td><a href=\"http://details.loinc.org/LOINC/11636-8.html\">11636-8</a></td><td>[#] Births.live</td></tr><tr><td><a href=\"http://details.loinc.org/LOINC/11637-6.html\">11637-6</a></td><td>[#] Births.preterm</td></tr><tr><td><a href=\"http://details.loinc.org/LOINC/11638-4.html\">11638-4</a></td><td>[#] Births.still living</td></tr><tr><td><a href=\"http://details.loinc.org/LOINC/11639-2.html\">11639-2</a></td><td>[#] Births.term</td></tr><tr><td><a href=\"http://details.loinc.org/LOINC/11640-0.html\">11640-0</a></td><td>[#] Births total</td></tr><tr><td><a href=\"http://details.loinc.org/LOINC/11612-9.html\">11612-9</a></td><td>[#] Abortions</td></tr><tr><td><a href=\"http://details.loinc.org/LOINC/11613-7.html\">11613-7</a></td><td>[#] Abortions.induced</td></tr><tr><td><a href=\"http://details.loinc.org/LOINC/11614-5.html\">11614-5</a></td><td>[#] Abortions.spontaneous</td></tr><tr><td><a href=\"http://details.loinc.org/LOINC/33065-4.html\">33065-4</a></td><td>[#] Ectopic pregnancy</td></tr></table></li></ul></div>"},"url":"http://hl7.org/fhir/uv/ips/ValueSet/pregnancies-summary-uv-ips","identifier":[{"use":"official","system":"http://art-decor.org/ns/oids/vs","value":"2.16.840.1.113883.11.22.21"}],"version":"1.0.0","name":"PregnanciesSummaryUvIps","title":"Pregnancies Summary - IPS","status":"active","experimental":false,"date":"2021-01-06T16:00:18+00:00","publisher":"Health Level Seven International - Patient Care Work Group","contact":[{"telecom":[{"system":"url","value":"http://www.hl7.org/Special/committees/patientcare"}]}],"description":"IPS Pregnancies Summary","jurisdiction":[{"coding":[{"system":"http://unstats.un.org/unsd/methods/m49/m49.htm","code":"001"}]}],"immutable":false,"copyright":"This artifact includes content from LOINC®. LOINC codes are copyright Regenstrief Institute, Inc. and the Logical Observation Identifiers Names and Codes (LOINC) Committee. Terms & Conditions in https://loinc.org/license/","compose":{"include":[{"system":"http://loinc.org","concept":[{"code":"11636-8","display":"[#] Births.live"},{"code":"11637-6","display":"[#] Births.preterm"},{"code":"11638-4","display":"[#] Births.still living"},{"code":"11639-2","display":"[#] Births.term"},{"code":"11640-0","display":"[#] Births total"},{"code":"11612-9","display":"[#] Abortions"},{"code":"11613-7","display":"[#] Abortions.induced"},{"code":"11614-5","display":"[#] Abortions.spontaneous"},{"code":"33065-4","display":"[#] Ectopic pregnancy"}]}]}}