{"resourceType":"Procedure","id":"mCODECancerRelatedSurgicalProcedureExample1","meta":{"profile":["http://hl7.org/fhir/us/mcode/StructureDefinition/mcode-cancer-related-surgical-procedure"]},"text":{"status":"extensions","div":"<div xmlns=\"http://www.w3.org/1999/xhtml\"><p><b>Generated Narrative</b></p><p><b>Treatment Intent</b>: <span title=\"Codes: {http://snomed.info/sct 373808002}\">Curative - procedure intent</span></p><p><b>status</b>: completed</p><p><b>category</b>: <span title=\"Codes: {http://snomed.info/sct 387713003}\">Surgical procedure (procedure)</span></p><p><b>code</b>: <span title=\"Codes: {http://snomed.info/sct 359615001}\">Partial lobectomy of lung (procedure)</span></p><p><b>subject</b>: <a href=\"Patient-mCODEPatientExample1.html\">Generated Summary: Medical Record Number: m123 (USUAL); John B. Anyperson ; gender: male; birthDate: 1951-01-20</a></p><p><b>performed</b>: 2019-03-01</p><p><b>asserter</b>: <a href=\"Practitioner-mCODEPractitionerExample1.html\">Generated Summary: id: 9988776655; Kyle Anydoc ; gender: male</a></p><p><b>reasonReference</b>: <a href=\"Condition-mCODEPrimaryCancerConditionExample1.html\">Generated Summary: <span title=\"Codes: {http://terminology.hl7.org/CodeSystem/condition-clinical active}\">Active</span>; <span title=\"Codes: {http://terminology.hl7.org/CodeSystem/condition-ver-status confirmed}\">Confirmed</span>; <span title=\"Codes: {http://terminology.hl7.org/CodeSystem/condition-category problem-list-item}\">Problem List Item</span>; <span title=\"Codes: {http://snomed.info/sct 254637007}\">Non-small cell lung cancer (disorder)</span>; <span title=\"Codes: {http://snomed.info/sct 39607008}\">Lung structure (body structure)</span>; onset: 2019-04-01</a></p><p><b>bodySite</b>: <span title=\"Codes: {http://snomed.info/sct 41224006}\">Structure of lower lobe of left lung (body structure)</span></p></div>"},"extension":[{"url":"http://hl7.org/fhir/us/mcode/StructureDefinition/mcode-treatment-intent","valueCodeableConcept":{"coding":[{"system":"http://snomed.info/sct","code":"373808002","display":"Curative - procedure intent"}]}}],"status":"completed","category":{"coding":[{"system":"http://snomed.info/sct","code":"387713003"}]},"code":{"coding":[{"system":"http://snomed.info/sct","code":"359615001","display":"Partial lobectomy of lung (procedure)"}]},"subject":{"reference":"Patient/mCODEPatientExample1"},"performedDateTime":"2019-03-01","asserter":{"reference":"Practitioner/mCODEPractitionerExample1"},"reasonReference":[{"reference":"Condition/mCODEPrimaryCancerConditionExample1"}],"bodySite":[{"coding":[{"system":"http://snomed.info/sct","code":"41224006","display":"Structure of lower lobe of left lung (body structure)"}]}]}